MANIFEST.in
README.md
setup.py
virtualensemble/LICENSE.html
virtualensemble/LICENSE.md
virtualensemble/README.md
virtualensemble/__init__.py
virtualensemble/__main__.py
virtualensemble/virtualensemble.py
virtualensemble.egg-info/PKG-INFO
virtualensemble.egg-info/SOURCES.txt
virtualensemble.egg-info/dependency_links.txt
virtualensemble.egg-info/entry_points.txt
virtualensemble.egg-info/requires.txt
virtualensemble.egg-info/top_level.txt
virtualensemble/gui/Info.ui
virtualensemble/gui/Info_UI.py
virtualensemble/gui/Virtualensemble.ui
virtualensemble/gui/Virtualensemble_UI.py
virtualensemble/gui/__init__.py
virtualensemble/media/DejaVuSerif.ttf
virtualensemble/media/Sync_track_for_backing.flac
virtualensemble/media/Sync_track_for_syncing.flac
virtualensemble/utils/__init__.py
virtualensemble/utils/qt_routines.py