Metadata-Version: 2.1
Name: virtualensemble
Version: 0.7.2
Summary: Easily create a mosaic virtual music piece
Home-page: UNKNOWN
Author: James Maggs
Author-email: EmailVirtualEnsemble@gmail.com
License: GNU General Public License v3.0
Platform: UNKNOWN
Classifier: License :: OSI Approved :: GNU General Public License v3 (GPLv3)
Classifier: Natural Language :: English
Classifier: Operating System :: OS Independent
Classifier: Programming Language :: Python :: 3
